requests_core/__init__.py
requests_core/api.py
requests_core/http_manager/__init__.py
requests_core/http_manager/_collections.py
requests_core/http_manager/base.py
requests_core/http_manager/connection.py
requests_core/http_manager/connectionpool.py
requests_core/http_manager/exceptions.py
requests_core/http_manager/fields.py
requests_core/http_manager/filepost.py
requests_core/http_manager/poolmanager.py
requests_core/http_manager/request.py
requests_core/http_manager/response.py
requests_core/http_manager/_async/__init__.py
requests_core/http_manager/_async/connection.py
requests_core/http_manager/_async/connectionpool.py
requests_core/http_manager/_async/poolmanager.py
requests_core/http_manager/_async/response.py
requests_core/http_manager/_backends/__init__.py
requests_core/http_manager/_backends/_common.py
requests_core/http_manager/_backends/sync_backend.py
requests_core/http_manager/_backends/trio_backend.py
requests_core/http_manager/_backends/twisted_backend.py
requests_core/http_manager/_sync/__init__.py
requests_core/http_manager/_sync/connection.py
requests_core/http_manager/_sync/connectionpool.py
requests_core/http_manager/_sync/poolmanager.py
requests_core/http_manager/_sync/response.py
requests_core/http_manager/contrib/__init__.py
requests_core/http_manager/contrib/appengine.py
requests_core/http_manager/contrib/pyopenssl.py
requests_core/http_manager/contrib/securetransport.py
requests_core/http_manager/contrib/socks.py
requests_core/http_manager/contrib/_securetransport/__init__.py
requests_core/http_manager/contrib/_securetransport/bindings.py
requests_core/http_manager/contrib/_securetransport/low_level.py
requests_core/http_manager/packages/__init__.py
requests_core/http_manager/packages/ordered_dict.py
requests_core/http_manager/packages/six.py
requests_core/http_manager/packages/backports/__init__.py
requests_core/http_manager/packages/backports/makefile.py
requestscore-0.0.0.dist-info/DESCRIPTION.rst
requestscore-0.0.0.dist-info/METADATA
requestscore-0.0.0.dist-info/RECORD
requestscore-0.0.0.dist-info/WHEEL
requestscore-0.0.0.dist-info/metadata.json
requestscore-0.0.0.dist-info/top_level.txt
